zolq/__init__.py
zolq/binding.py
zolq/cli.py
zolq/adapters/__init__.py
zolq/adapters/qiskit_counts.py
zolq-0.0.5.dist-info/METADATA
zolq-0.0.5.dist-info/WHEEL
zolq-0.0.5.dist-info/entry_points.txt
zolq-0.0.5.dist-info/top_level.txt
zolq-0.0.5.dist-info/RECORD
